src/__init__.py
src/mathematical.py
python_comparator-0.0.2.dist-info/LICENSE
python_comparator-0.0.2.dist-info/METADATA
python_comparator-0.0.2.dist-info/WHEEL
python_comparator-0.0.2.dist-info/top_level.txt
python_comparator-0.0.2.dist-info/RECORD
