Metadata-Version: 2.1
Name: python-comparator
Version: 0.0.2
Summary: My first Python package
Home-page: https://github.com/gituser/test-tackage
Author: Sanyam Arya
Author-email: er.sanyam.arya@gmail.com
License: MIT
Keywords: python,compare,compare values
Platform: UNKNOWN
Classifier: Programming Language :: Python :: 3
Classifier: License :: OSI Approved :: MIT License
Classifier: Operating System :: OS Independent
Requires-Python: >=3
